airow/__init__.py
airow/agent.py
airow/airow.py
airow/schemas.py
airow-0.1.0.dist-info/licenses/LICENSE
airow-0.1.0.dist-info/METADATA
airow-0.1.0.dist-info/WHEEL
airow-0.1.0.dist-info/top_level.txt
airow-0.1.0.dist-info/RECORD
