Metadata-Version: 2.4
Name: airow
Version: 0.1.0
Summary: AI-powered DataFrame processing made simple
Author-email: Dmitrii K <dmitriik@protonmail.com>
Maintainer-email: Dmitrii K <dmitriik@protonmail.com>
License: MIT
Project-URL: Homepage, https://github.com/dmitriiweb/airow
Project-URL: Repository, https://github.com/dmitriiweb/airow
Project-URL: Documentation, https://github.com/dmitriiweb/airow
Project-URL: Bug Tracker, https://github.com/dmitriiweb/airow/issues
Keywords: ai,ai-agent,dataframe,pandas,pydantic-ai,async,data-processing
Classifier: Development Status :: 5 - Production/Stable
Classifier: Intended Audience :: Developers
Classifier: Intended Audience :: Science/Research
Classifier: License :: OSI Approved :: MIT License
Classifier: Operating System :: OS Independent
Classifier: Programming Language :: Python :: 3
Classifier: Programming Language :: Python :: 3.10
Classifier: Programming Language :: Python :: 3.11
Classifier: Programming Language :: Python :: 3.12
Classifier: Programming Language :: Python :: 3.13
Classifier: Topic :: Scientific/Engineering :: Artificial Intelligence
Classifier: Topic :: Scientific/Engineering :: Information Analysis
Classifier: Topic :: Software Development :: Libraries :: Python Modules
Classifier: Topic :: Text Processing
Classifier: Topic :: Database
Classifier: Typing :: Typed
Requires-Python: >=3.10
License-File: LICENSE
Requires-Dist: loguru>=0.7.3
Requires-Dist: pandas>=2.3.2
Requires-Dist: pydantic>=2.11.7
Requires-Dist: pydantic-ai>=0.8.1
Requires-Dist: tqdm>=4.67.1
Provides-Extra: dev
Requires-Dist: mypy>=1.17.1; extra == "dev"
Requires-Dist: pytest>=8.4.2; extra == "dev"
Requires-Dist: pytest-asyncio>=1.1.0; extra == "dev"
Requires-Dist: pytest-cov>=6.3.0; extra == "dev"
Requires-Dist: ruff>=0.12.12; extra == "dev"
Dynamic: license-file
